{"cameraMode":{"drawMode":0,"name":"Shaded","section":"Shading Mode"},"sceneLighting":true,"audioPlay":false,"sceneViewState":{"m_AlwaysRefresh":false,"showFog":true,"showSkybox":true,"showFlares":true,"showImageEffects":true,"showParticleSystems":true,"showVisualEffectGraphs":true,"m_FxEnabled":true},"in2DMode":false,"pivot":{"x":32.82903289794922,"y":19.10453224182129,"z":-17.373729705810548},"rotation":{"x":0.2398945391178131,"y":-0.46155738830566409,"z":0.13113678991794587,"w":0.8440216183662415},"size":4.105126857757568,"orthographic":false}