{"cameraMode":{"drawMode":0,"name":"Shaded","section":"Shading Mode"},"sceneLighting":false,"audioPlay":false,"sceneViewState":{"m_AlwaysRefresh":false,"showFog":true,"showSkybox":false,"showFlares":true,"showImageEffects":true,"showParticleSystems":true,"showVisualEffectGraphs":true,"m_FxEnabled":true},"in2DMode":false,"pivot":{"x":0.22074635326862336,"y":0.3580532670021057,"z":0.3854893445968628},"rotation":{"x":0.008156821131706238,"y":-0.9758145809173584,"z":0.21342960000038148,"w":0.05467778816819191},"size":0.8660253882408142,"orthographic":false}